PyTangtv-1.0.31.data/scripts/picker
PyTangtv-1.0.31.data/scripts/pyalign
PyTangtv-1.0.31.data/scripts/pymask
PyTangtv-1.0.31.data/scripts/pymorph
pytangtv/__init__.py
pytangtv/check4updates.py
pytangtv/bitmaps/add.png
pytangtv/bitmaps/down.xbm
pytangtv/bitmaps/freeze.png
pytangtv/bitmaps/frozen.png
pytangtv/bitmaps/left.xbm
pytangtv/bitmaps/morphoff.png
pytangtv/bitmaps/morphon.png
pytangtv/bitmaps/right.xbm
pytangtv/bitmaps/rotl.xbm
pytangtv/bitmaps/rotr.xbm
pytangtv/bitmaps/up.xbm
pytangtv/picker/__init__.py
pytangtv/picker/cpcracks.py
pytangtv/picker/cylcracks.py
pytangtv/picker/rm1cracks.py
pytangtv/picker/rm2cracks.py
pytangtv/picker/spots_lower.py
pytangtv/picker/spots_upper.py
pytangtv/picker/spots_upper_sas.py
pytangtv/pyalign/__init__.py
pytangtv/pyalign/controls.py
pytangtv/pyalign/menu.py
pytangtv/pymask/__init__.py
pytangtv/pymask/controls.py
pytangtv/pymorph/Polywarp.py
pytangtv/pymorph/__init__.py
pytangtv/pymorph/bytescale.py
pytangtv/pymorph/controls.py
pytangtv/pymorph/help.py
pytangtv/pymorph/mapD3DSeperatrix.py
pytangtv/pymorph/menu.py
pytangtv/pymorph/morphimage.py
pytangtv/pymorph/testmorph.py
PyTangtv-1.0.31.dist-info/METADATA
PyTangtv-1.0.31.dist-info/WHEEL
PyTangtv-1.0.31.dist-info/top_level.txt
PyTangtv-1.0.31.dist-info/RECORD
