Metadata-Version: 2.1
Name: PyTangtv
Version: 1.0.31
Summary: LLNL DIII-D diagnostic image tools
Maintainer: Bill Meyer
Maintainer-email: meyer8@llnl.gov
License: LLNL
Classifier: Programming Language :: Python
Classifier: Programming Language :: Python :: 3
Requires-Dist: requests
Requires-Dist: pyyaml
Requires-Dist: numpy
Requires-Dist: scipy
Requires-Dist: Pillow
Requires-Dist: packaging
Requires-Dist: tk
